setup.py
file_upload/__init__.py
file_upload/file_client.py
file_upload/upload.py
my_upload.egg-info/PKG-INFO
my_upload.egg-info/SOURCES.txt
my_upload.egg-info/dependency_links.txt
my_upload.egg-info/entry_points.txt
my_upload.egg-info/top_level.txt