Metadata-Version: 1.2
Name: my-upload
Version: 2.0.0
Summary: 上传文件到文件系统
Home-page: UNKNOWN
Author: hxl
Maintainer: hxl
License: MIT License
Platform: UNKNOWN
Classifier: Programming Language :: Python :: 3
Classifier: License :: OSI Approved :: MIT License
Classifier: Operating System :: OS Independent
